blends/__init__.py
blends/models.py
blends/py.typed
blends/ast/__init__.py
blends/ast/build_graph.py
blends/content/__init__.py
blends/content/content.py
blends/content/custom_parsers/__init__.py
blends/content/custom_parsers/helm_templates.py
blends/ctx/__init__.py
blends/query/__init__.py
blends/stack/__init__.py
blends/stack/attributes.py
blends/stack/criteria.py
blends/stack/edges.py
blends/stack/forward_stitcher.py
blends/stack/node_helpers.py
blends/stack/node_kinds.py
blends/stack/partial_path_database.py
blends/stack/partial_path_db.py
blends/stack/partial_path_indexer.py
blends/stack/selection.py
blends/stack/single_file_resolver.py
blends/stack/stacks.py
blends/stack/transitions.py
blends/stack/validation.py
blends/stack/view.py
blends/stack/partial_path/__init__.py
blends/stack/partial_path/bindings.py
blends/stack/partial_path/errors.py
blends/stack/partial_path/half_open.py
blends/stack/partial_path/minimal_paths.py
blends/stack/partial_path/partial_path.py
blends/stack/partial_path/partial_stacks.py
blends/stack/partial_path/stack_conditions.py
blends/stack/partial_path/variables.py
blends/static/__init__.py
blends/static/node_types/__init__.py
blends/static/node_types/c_sharp-fields.json
blends/static/node_types/dart-fields.json
blends/static/node_types/go-fields.json
blends/static/node_types/hcl-fields.json
blends/static/node_types/java-fields.json
blends/static/node_types/javascript-fields.json
blends/static/node_types/json-fields.json
blends/static/node_types/kotlin-fields.json
blends/static/node_types/php-fields.json
blends/static/node_types/python-fields.json
blends/static/node_types/ruby-fields.json
blends/static/node_types/scala-fields.json
blends/static/node_types/swift-fields.json
blends/static/node_types/tsx-fields.json
blends/static/node_types/yaml-fields.json
blends/symbolic_evaluation/__init__.py
blends/symbolic_evaluation/common.py
blends/symbolic_evaluation/dispatcher.py
blends/symbolic_evaluation/evaluate.py
fluid_blends-0.7.1.dist-info/METADATA
fluid_blends-0.7.1.dist-info/WHEEL
fluid_blends-0.7.1.dist-info/RECORD
