Metadata-Version: 2.4
Name: fluid-blends
Version: 0.7.1
Summary: A Python library to generate and query ASTs, CFGs, and syntax graphs from multi-language source code
Author-email: Fluid Attacks Development Team <development@fluidattacks.com>
Requires-Python: <4.0,>=3.11
Requires-Dist: networkx==3.6.1
Requires-Dist: sympy==1.14.0
Requires-Dist: tree-sitter-c-sharp==0.23.1
Requires-Dist: tree-sitter-dart-orchard==0.3.2
Requires-Dist: tree-sitter-go==0.23.4
Requires-Dist: tree-sitter-hcl==1.2.0
Requires-Dist: tree-sitter-java==0.23.5
Requires-Dist: tree-sitter-javascript==0.23.1
Requires-Dist: tree-sitter-json==0.24.8
Requires-Dist: tree-sitter-kotlin==1.1.0
Requires-Dist: tree-sitter-php==0.23.11
Requires-Dist: tree-sitter-python==0.23.6
Requires-Dist: tree-sitter-ruby==0.23.1
Requires-Dist: tree-sitter-scala==0.23.4
Requires-Dist: tree-sitter-swift==0.0.1
Requires-Dist: tree-sitter-typescript==0.23.2
Requires-Dist: tree-sitter-yaml==0.7.0
Requires-Dist: tree-sitter==0.25.2
